MANIFEST.in
README.md
requirements.txt
setup.py
mw_feature_serving_sdk.egg-info/PKG-INFO
mw_feature_serving_sdk.egg-info/SOURCES.txt
mw_feature_serving_sdk.egg-info/dependency_links.txt
mw_feature_serving_sdk.egg-info/requires.txt
mw_feature_serving_sdk.egg-info/top_level.txt
mwfeatureserving/__init__.py
mwfeatureserving/config.py
mwfeatureserving/mw_feature_store.py
mwfeatureserving/services/__init__.py
mwfeatureserving/services/mwfs_api.py
mwfeatureserving/util/__init__.py
mwfeatureserving/util/common_util.py
mwfeatureserving/util/repo_config_util.py
mwfeatureserving/util/requests_util.py
tests/__init__.py