Metadata-Version: 2.1
Name: mw-feature-serving-sdk
Version: 0.1
Summary: An SDK to access Mobilewalla's Feature Machine service
Home-page: https://www.mobilewalla.com
Author: Mobilewalla Feature Store
Author-email: feature-store@mobilewalla.com
License: UNKNOWN
Platform: UNKNOWN
Requires-Python: >=3.7
